{
  "&color": {
    "primary": {
      "primary": {
        "$type": "color",
        "$value": {
          "colorSpace": "srgb",
          "components": [
            0.7372549176216125,
            0.7647058963775635,
            1
          ],
          "alpha": 1,
          "hex": "#BCC3FF"
        },
        "$extensions": {
          "com.figma.variableId": "VariableID:2356:22762",
          "com.figma.scopes": [
            "ALL_SCOPES"
          ],
          "com.figma.aliasData": {
            "targetVariableId": "VariableID:9399883f6c365659987d6621e53f67929dcfa6ad/-1:-1",
            "targetVariableName": "indigo/80",
            "targetVariableSetId": "VariableCollectionId:83ba552c2f0e2d8b20b04cfcef7f4a43c3163632/-1:-1",
            "targetVariableSetName": "& color hero"
          }
        }
      },
      "primaryHover": {
        "$type": "color",
        "$value": {
          "colorSpace": "srgb",
          "components": [
            0.5960784554481506,
            0.6431372761726379,
            1
          ],
          "alpha": 1,
          "hex": "#98A4FF"
        },
        "$extensions": {
          "com.figma.variableId": "VariableID:2391:32206",
          "com.figma.scopes": [
            "ALL_SCOPES"
          ],
          "com.figma.aliasData": {
            "targetVariableId": "VariableID:1eec092324225638b0d23c459a9f451dd69f2848/-1:-1",
            "targetVariableName": "indigo/70",
            "targetVariableSetId": "VariableCollectionId:83ba552c2f0e2d8b20b04cfcef7f4a43c3163632/-1:-1",
            "targetVariableSetName": "& color hero"
          }
        }
      },
      "primaryPress": {
        "$type": "color",
        "$value": {
          "colorSpace": "srgb",
          "components": [
            0.4588235318660736,
            0.5254902243614197,
            1
          ],
          "alpha": 1,
          "hex": "#7586FF"
        },
        "$extensions": {
          "com.figma.variableId": "VariableID:2391:32207",
          "com.figma.scopes": [
            "ALL_SCOPES"
          ],
          "com.figma.aliasData": {
            "targetVariableId": "VariableID:1b9202c8091fd004e4239b861d00dd1c51b69759/-1:-1",
            "targetVariableName": "indigo/60",
            "targetVariableSetId": "VariableCollectionId:83ba552c2f0e2d8b20b04cfcef7f4a43c3163632/-1:-1",
            "targetVariableSetName": "& color hero"
          }
        }
      },
      "primaryOverlay": {
        "$type": "color",
        "$value": {
          "colorSpace": "srgb",
          "components": [
            0.3137255012989044,
            0.4000000059604645,
            1
          ],
          "alpha": 0.3799999952316284,
          "hex": "#5066FF"
        },
        "$extensions": {
          "com.figma.variableId": "VariableID:2357:22806",
          "com.figma.scopes": [
            "ALL_SCOPES"
          ],
          "com.figma.aliasData": {
            "targetVariableId": "VariableID:37f791e39ad16a0f052f7418398eebc428fb0ff8/-1:-1",
            "targetVariableName": "indigo/alphaLightest",
            "targetVariableSetId": "VariableCollectionId:83ba552c2f0e2d8b20b04cfcef7f4a43c3163632/-1:-1",
            "targetVariableSetName": "& color hero"
          }
        }
      },
      "primaryOverlayHover": {
        "$type": "color",
        "$value": {
          "colorSpace": "srgb",
          "components": [
            0.3137255012989044,
            0.4000000059604645,
            1
          ],
          "alpha": 0.30000001192092896,
          "hex": "#5066FF"
        },
        "$extensions": {
          "com.figma.variableId": "VariableID:2480:16969",
          "com.figma.scopes": [
            "ALL_SCOPES"
          ],
          "com.figma.aliasData": {
            "targetVariableId": "VariableID:a3c3f56be1120e91badbbfe30c89894d218743cf/-1:-1",
            "targetVariableName": "indigo/alphaLighter",
            "targetVariableSetId": "VariableCollectionId:83ba552c2f0e2d8b20b04cfcef7f4a43c3163632/-1:-1",
            "targetVariableSetName": "& color hero"
          }
        }
      },
      "primaryOverlayPress": {
        "$type": "color",
        "$value": {
          "colorSpace": "srgb",
          "components": [
            0.3137255012989044,
            0.4000000059604645,
            1
          ],
          "alpha": 0.2199999988079071,
          "hex": "#5066FF"
        },
        "$extensions": {
          "com.figma.variableId": "VariableID:5660:42603",
          "com.figma.scopes": [
            "ALL_SCOPES"
          ],
          "com.figma.aliasData": {
            "targetVariableId": "VariableID:ca89cc35bc8dd97b3bd39619832b1b753b475de5/-1:-1",
            "targetVariableName": "indigo/alphaLight",
            "targetVariableSetId": "VariableCollectionId:83ba552c2f0e2d8b20b04cfcef7f4a43c3163632/-1:-1",
            "targetVariableSetName": "& color hero"
          }
        }
      }
    },
    "secondary": {
      "secondary": {
        "$type": "color",
        "$value": {
          "colorSpace": "srgb",
          "components": [
            1,
            1,
            1
          ],
          "alpha": 1,
          "hex": "#FFFFFF"
        },
        "$extensions": {
          "com.figma.variableId": "VariableID:2438:26718",
          "com.figma.scopes": [
            "ALL_SCOPES"
          ],
          "com.figma.aliasData": {
            "targetVariableId": "VariableID:f481f844daaac7fae12dab4d7a30ddaff3838e80/-1:-1",
            "targetVariableName": "white/white",
            "targetVariableSetId": "VariableCollectionId:83ba552c2f0e2d8b20b04cfcef7f4a43c3163632/-1:-1",
            "targetVariableSetName": "& color hero"
          }
        }
      },
      "secondaryHover": {
        "$type": "color",
        "$value": {
          "colorSpace": "srgb",
          "components": [
            0.8901960849761963,
            0.8901960849761963,
            0.8901960849761963
          ],
          "alpha": 1,
          "hex": "#E3E3E3"
        },
        "$extensions": {
          "com.figma.variableId": "VariableID:2438:26719",
          "com.figma.scopes": [
            "ALL_SCOPES"
          ],
          "com.figma.aliasData": {
            "targetVariableId": "VariableID:fed7b18f3b54daafb0d85a10951384bf99bcd3e6/-1:-1",
            "targetVariableName": "pure neutral/90",
            "targetVariableSetId": "VariableCollectionId:83ba552c2f0e2d8b20b04cfcef7f4a43c3163632/-1:-1",
            "targetVariableSetName": "& color hero"
          }
        }
      },
      "secondaryPress": {
        "$type": "color",
        "$value": {
          "colorSpace": "srgb",
          "components": [
            0.6705882549285889,
            0.6705882549285889,
            0.6705882549285889
          ],
          "alpha": 1,
          "hex": "#ABABAB"
        },
        "$extensions": {
          "com.figma.variableId": "VariableID:2438:26720",
          "com.figma.scopes": [
            "ALL_SCOPES"
          ],
          "com.figma.aliasData": {
            "targetVariableId": "VariableID:1dad3afbcfe81986efaf0427bc8d840205e1a6c1/-1:-1",
            "targetVariableName": "pure neutral/70",
            "targetVariableSetId": "VariableCollectionId:83ba552c2f0e2d8b20b04cfcef7f4a43c3163632/-1:-1",
            "targetVariableSetName": "& color hero"
          }
        }
      },
      "secondaryOverlay": {
        "$type": "color",
        "$value": {
          "colorSpace": "srgb",
          "components": [
            0.5529412031173706,
            0.5607843399047852,
            0.5960784554481506
          ],
          "alpha": 0.11999999731779099,
          "hex": "#8D8F98"
        },
        "$extensions": {
          "com.figma.variableId": "VariableID:2438:26721",
          "com.figma.scopes": [
            "ALL_SCOPES"
          ],
          "com.figma.aliasData": {
            "targetVariableId": "VariableID:db3dc00cb6a4d3e7671619e41378ba583a5fae0a/-1:-1",
            "targetVariableName": "cool neutral/alphaLight",
            "targetVariableSetId": "VariableCollectionId:83ba552c2f0e2d8b20b04cfcef7f4a43c3163632/-1:-1",
            "targetVariableSetName": "& color hero"
          }
        }
      },
      "secondaryOverlayHover": {
        "$type": "color",
        "$value": {
          "colorSpace": "srgb",
          "components": [
            0.5529412031173706,
            0.5607843399047852,
            0.5960784554481506
          ],
          "alpha": 0.18000000715255737,
          "hex": "#8D8F98"
        },
        "$extensions": {
          "com.figma.variableId": "VariableID:2480:16970",
          "com.figma.scopes": [
            "ALL_SCOPES"
          ],
          "com.figma.aliasData": {
            "targetVariableId": "VariableID:c8faaaece2c60c44d921747e2bed6af9324fc613/-1:-1",
            "targetVariableName": "cool neutral/alphaLighter",
            "targetVariableSetId": "VariableCollectionId:83ba552c2f0e2d8b20b04cfcef7f4a43c3163632/-1:-1",
            "targetVariableSetName": "& color hero"
          }
        }
      }
    },
    "tonal": {
      "tonal": {
        "$type": "color",
        "$value": {
          "colorSpace": "srgb",
          "components": [
            0.07450980693101883,
            0.13725490868091583,
            0.5176470875740051
          ],
          "alpha": 1,
          "hex": "#132384"
        },
        "$extensions": {
          "com.figma.variableId": "VariableID:3856:2939",
          "com.figma.scopes": [
            "ALL_SCOPES"
          ],
          "com.figma.aliasData": {
            "targetVariableId": "VariableID:5704a58b8ab3e99dfa8dc227f23271f0fa795c86/-1:-1",
            "targetVariableName": "indigo/20",
            "targetVariableSetId": "VariableCollectionId:83ba552c2f0e2d8b20b04cfcef7f4a43c3163632/-1:-1",
            "targetVariableSetName": "& color hero"
          }
        }
      },
      "tonalHover": {
        "$type": "color",
        "$value": {
          "colorSpace": "srgb",
          "components": [
            0.5960784554481506,
            0.6431372761726379,
            1
          ],
          "alpha": 1,
          "hex": "#98A4FF"
        },
        "$extensions": {
          "com.figma.variableId": "VariableID:3856:2940",
          "com.figma.scopes": [
            "ALL_SCOPES"
          ],
          "com.figma.aliasData": {
            "targetVariableId": "VariableID:1eec092324225638b0d23c459a9f451dd69f2848/-1:-1",
            "targetVariableName": "indigo/70",
            "targetVariableSetId": "VariableCollectionId:83ba552c2f0e2d8b20b04cfcef7f4a43c3163632/-1:-1",
            "targetVariableSetName": "& color hero"
          }
        }
      },
      "tonalPress": {
        "$type": "color",
        "$value": {
          "colorSpace": "srgb",
          "components": [
            0.4588235318660736,
            0.5254902243614197,
            1
          ],
          "alpha": 1,
          "hex": "#7586FF"
        },
        "$extensions": {
          "com.figma.variableId": "VariableID:3856:2941",
          "com.figma.scopes": [
            "ALL_SCOPES"
          ],
          "com.figma.aliasData": {
            "targetVariableId": "VariableID:1b9202c8091fd004e4239b861d00dd1c51b69759/-1:-1",
            "targetVariableName": "indigo/60",
            "targetVariableSetId": "VariableCollectionId:83ba552c2f0e2d8b20b04cfcef7f4a43c3163632/-1:-1",
            "targetVariableSetName": "& color hero"
          }
        }
      },
      "tonalLightest": {
        "$type": "color",
        "$value": {
          "colorSpace": "srgb",
          "components": [
            0.3137255012989044,
            0.4000000059604645,
            1
          ],
          "alpha": 0.3799999952316284,
          "hex": "#5066FF"
        },
        "$extensions": {
          "com.figma.variableId": "VariableID:5003:16931",
          "com.figma.scopes": [
            "ALL_SCOPES"
          ],
          "com.figma.aliasData": {
            "targetVariableId": "VariableID:37f791e39ad16a0f052f7418398eebc428fb0ff8/-1:-1",
            "targetVariableName": "indigo/alphaLightest",
            "targetVariableSetId": "VariableCollectionId:83ba552c2f0e2d8b20b04cfcef7f4a43c3163632/-1:-1",
            "targetVariableSetName": "& color hero"
          }
        }
      },
      "tonalOverlay": {
        "$type": "color",
        "$value": {
          "colorSpace": "srgb",
          "components": [
            0.3137255012989044,
            0.4000000059604645,
            1
          ],
          "alpha": 0.30000001192092896,
          "hex": "#5066FF"
        },
        "$extensions": {
          "com.figma.variableId": "VariableID:3856:2942",
          "com.figma.scopes": [
            "ALL_SCOPES"
          ],
          "com.figma.aliasData": {
            "targetVariableId": "VariableID:a3c3f56be1120e91badbbfe30c89894d218743cf/-1:-1",
            "targetVariableName": "indigo/alphaLighter",
            "targetVariableSetId": "VariableCollectionId:83ba552c2f0e2d8b20b04cfcef7f4a43c3163632/-1:-1",
            "targetVariableSetName": "& color hero"
          }
        }
      },
      "tonalOverlayHover": {
        "$type": "color",
        "$value": {
          "colorSpace": "srgb",
          "components": [
            0.3137255012989044,
            0.4000000059604645,
            1
          ],
          "alpha": 0.2199999988079071,
          "hex": "#5066FF"
        },
        "$extensions": {
          "com.figma.variableId": "VariableID:3856:2943",
          "com.figma.scopes": [
            "ALL_SCOPES"
          ],
          "com.figma.aliasData": {
            "targetVariableId": "VariableID:ca89cc35bc8dd97b3bd39619832b1b753b475de5/-1:-1",
            "targetVariableName": "indigo/alphaLight",
            "targetVariableSetId": "VariableCollectionId:83ba552c2f0e2d8b20b04cfcef7f4a43c3163632/-1:-1",
            "targetVariableSetName": "& color hero"
          }
        }
      },
      "tonalOverlayPress": {
        "$type": "color",
        "$value": {
          "colorSpace": "srgb",
          "components": [
            0.3137255012989044,
            0.4000000059604645,
            1
          ],
          "alpha": 0.2199999988079071,
          "hex": "#5066FF"
        },
        "$extensions": {
          "com.figma.variableId": "VariableID:3861:3585",
          "com.figma.scopes": [
            "ALL_SCOPES"
          ],
          "com.figma.aliasData": {
            "targetVariableId": "VariableID:ca89cc35bc8dd97b3bd39619832b1b753b475de5/-1:-1",
            "targetVariableName": "indigo/alphaLight",
            "targetVariableSetId": "VariableCollectionId:83ba552c2f0e2d8b20b04cfcef7f4a43c3163632/-1:-1",
            "targetVariableSetName": "& color hero"
          }
        }
      },
      "tonalSecondaryOverlay": {
        "$type": "color",
        "$value": {
          "colorSpace": "srgb",
          "components": [
            0.364705890417099,
            0.3686274588108063,
            0.40392157435417175
          ],
          "alpha": 0.18000000715255737,
          "hex": "#5D5E67"
        },
        "$extensions": {
          "com.figma.variableId": "VariableID:4116:1766",
          "com.figma.scopes": [
            "ALL_SCOPES"
          ],
          "com.figma.aliasData": {
            "targetVariableId": "VariableID:e3d20aa1f2c222edff4089b9cda8279e461350a2/-1:-1",
            "targetVariableName": "cool neutral/alphaDarker",
            "targetVariableSetId": "VariableCollectionId:83ba552c2f0e2d8b20b04cfcef7f4a43c3163632/-1:-1",
            "targetVariableSetName": "& color hero"
          }
        }
      },
      "tonalSecondaryOverlayHover": {
        "$type": "color",
        "$value": {
          "colorSpace": "srgb",
          "components": [
            0.5529412031173706,
            0.5607843399047852,
            0.5960784554481506
          ],
          "alpha": 0.11999999731779099,
          "hex": "#8D8F98"
        },
        "$extensions": {
          "com.figma.variableId": "VariableID:4116:5250",
          "com.figma.scopes": [
            "ALL_SCOPES"
          ],
          "com.figma.aliasData": {
            "targetVariableId": "VariableID:db3dc00cb6a4d3e7671619e41378ba583a5fae0a/-1:-1",
            "targetVariableName": "cool neutral/alphaLight",
            "targetVariableSetId": "VariableCollectionId:83ba552c2f0e2d8b20b04cfcef7f4a43c3163632/-1:-1",
            "targetVariableSetName": "& color hero"
          }
        }
      },
      "tonalSecondaryOverlayPress": {
        "$type": "color",
        "$value": {
          "colorSpace": "srgb",
          "components": [
            0.5529412031173706,
            0.5607843399047852,
            0.5960784554481506
          ],
          "alpha": 0.18000000715255737,
          "hex": "#8D8F98"
        },
        "$extensions": {
          "com.figma.variableId": "VariableID:4116:5251",
          "com.figma.scopes": [
            "ALL_SCOPES"
          ],
          "com.figma.aliasData": {
            "targetVariableId": "VariableID:c8faaaece2c60c44d921747e2bed6af9324fc613/-1:-1",
            "targetVariableName": "cool neutral/alphaLighter",
            "targetVariableSetId": "VariableCollectionId:83ba552c2f0e2d8b20b04cfcef7f4a43c3163632/-1:-1",
            "targetVariableSetName": "& color hero"
          }
        }
      }
    },
    "info": {
      "info": {
        "$type": "color",
        "$value": {
          "colorSpace": "srgb",
          "components": [
            0.6549019813537598,
            0.7843137383460999,
            0.9960784316062927
          ],
          "alpha": 1,
          "hex": "#A7C8FE"
        },
        "$extensions": {
          "com.figma.variableId": "VariableID:2908:9405",
          "com.figma.scopes": [
            "ALL_SCOPES"
          ],
          "com.figma.aliasData": {
            "targetVariableId": "VariableID:7aaf746cadc503736aac87b0dc8189d6409976c0/-1:-1",
            "targetVariableName": "blue/80",
            "targetVariableSetId": "VariableCollectionId:83ba552c2f0e2d8b20b04cfcef7f4a43c3163632/-1:-1",
            "targetVariableSetName": "& color hero"
          }
        }
      },
      "infoOverlay": {
        "$type": "color",
        "$value": {
          "colorSpace": "srgb",
          "components": [
            0.23137255012989044,
            0.572549045085907,
            0.9764705896377563
          ],
          "alpha": 0.18000000715255737,
          "hex": "#3B92F9"
        },
        "$extensions": {
          "com.figma.variableId": "VariableID:2908:9406",
          "com.figma.scopes": [
            "ALL_SCOPES"
          ],
          "com.figma.aliasData": {
            "targetVariableId": "VariableID:003760f77e7f7fe8481ee431b6637d9c7212359e/-1:-1",
            "targetVariableName": "blue/alphaLighter",
            "targetVariableSetId": "VariableCollectionId:83ba552c2f0e2d8b20b04cfcef7f4a43c3163632/-1:-1",
            "targetVariableSetName": "& color hero"
          }
        }
      },
      "infoOverlayHover": {
        "$type": "color",
        "$value": {
          "colorSpace": "srgb",
          "components": [
            0.23137255012989044,
            0.572549045085907,
            0.9764705896377563
          ],
          "alpha": 0.11999999731779099,
          "hex": "#3B92F9"
        },
        "$extensions": {
          "com.figma.variableId": "VariableID:2913:9192",
          "com.figma.scopes": [
            "ALL_SCOPES"
          ],
          "com.figma.aliasData": {
            "targetVariableId": "VariableID:7352a7a70a03ca8b954712c370dff64ab21b724f/-1:-1",
            "targetVariableName": "blue/alphaLight",
            "targetVariableSetId": "VariableCollectionId:83ba552c2f0e2d8b20b04cfcef7f4a43c3163632/-1:-1",
            "targetVariableSetName": "& color hero"
          }
        }
      }
    },
    "success": {
      "success": {
        "$type": "color",
        "$value": {
          "colorSpace": "srgb",
          "components": [
            0.5176470875740051,
            0.8588235378265381,
            0.3960784375667572
          ],
          "alpha": 1,
          "hex": "#84DB65"
        },
        "$extensions": {
          "com.figma.variableId": "VariableID:2475:7979",
          "com.figma.scopes": [
            "ALL_SCOPES"
          ],
          "com.figma.aliasData": {
            "targetVariableId": "VariableID:17ddffd386fcd108040e483806c25106d0bc3aeb/-1:-1",
            "targetVariableName": "green/80",
            "targetVariableSetId": "VariableCollectionId:83ba552c2f0e2d8b20b04cfcef7f4a43c3163632/-1:-1",
            "targetVariableSetName": "& color hero"
          }
        }
      },
      "successOverlay": {
        "$type": "color",
        "$value": {
          "colorSpace": "srgb",
          "components": [
            0.29019609093666077,
            0.6431372761726379,
            0.1725490242242813
          ],
          "alpha": 0.18000000715255737,
          "hex": "#4AA42C"
        },
        "$extensions": {
          "com.figma.variableId": "VariableID:2475:7980",
          "com.figma.scopes": [
            "ALL_SCOPES"
          ],
          "com.figma.aliasData": {
            "targetVariableId": "VariableID:af95a3261d281ccb0b96b48e66c24453c0857171/-1:-1",
            "targetVariableName": "green/alphaLighter",
            "targetVariableSetId": "VariableCollectionId:83ba552c2f0e2d8b20b04cfcef7f4a43c3163632/-1:-1",
            "targetVariableSetName": "& color hero"
          }
        }
      },
      "successOverlayHover": {
        "$type": "color",
        "$value": {
          "colorSpace": "srgb",
          "components": [
            0.29019609093666077,
            0.6431372761726379,
            0.1725490242242813
          ],
          "alpha": 0.11999999731779099,
          "hex": "#4AA42C"
        },
        "$extensions": {
          "com.figma.variableId": "VariableID:2913:9175",
          "com.figma.scopes": [
            "ALL_SCOPES"
          ],
          "com.figma.aliasData": {
            "targetVariableId": "VariableID:b961d42a32f29d92524108fb4d5d06b302b0ebe5/-1:-1",
            "targetVariableName": "green/alphaLight",
            "targetVariableSetId": "VariableCollectionId:83ba552c2f0e2d8b20b04cfcef7f4a43c3163632/-1:-1",
            "targetVariableSetName": "& color hero"
          }
        }
      }
    },
    "warning": {
      "warn": {
        "$type": "color",
        "$value": {
          "colorSpace": "srgb",
          "components": [
            1,
            0.5490196347236633,
            0.364705890417099
          ],
          "alpha": 1,
          "hex": "#FF8C5D"
        },
        "$extensions": {
          "com.figma.variableId": "VariableID:2475:7981",
          "com.figma.scopes": [
            "ALL_SCOPES"
          ],
          "com.figma.aliasData": {
            "targetVariableId": "VariableID:be2d4520f737e2a16039805267e1fd201e37705e/-1:-1",
            "targetVariableName": "orange/70",
            "targetVariableSetId": "VariableCollectionId:83ba552c2f0e2d8b20b04cfcef7f4a43c3163632/-1:-1",
            "targetVariableSetName": "& color hero"
          }
        }
      },
      "warnOverlay": {
        "$type": "color",
        "$value": {
          "colorSpace": "srgb",
          "components": [
            0.9882352948188782,
            0.7333333492279053,
            0.25882354378700256
          ],
          "alpha": 0.18000000715255737,
          "hex": "#FCBB42"
        },
        "$extensions": {
          "com.figma.variableId": "VariableID:2475:7982",
          "com.figma.scopes": [
            "ALL_SCOPES"
          ],
          "com.figma.aliasData": {
            "targetVariableId": "VariableID:32b856343b982d81b03291d6e686e5711aad33d2/-1:-1",
            "targetVariableName": "gold/alphaLighter",
            "targetVariableSetId": "VariableCollectionId:83ba552c2f0e2d8b20b04cfcef7f4a43c3163632/-1:-1",
            "targetVariableSetName": "& color hero"
          }
        }
      },
      "warnOverlayHover": {
        "$type": "color",
        "$value": {
          "colorSpace": "srgb",
          "components": [
            0.9882352948188782,
            0.7333333492279053,
            0.25882354378700256
          ],
          "alpha": 0.11999999731779099,
          "hex": "#FCBB42"
        },
        "$extensions": {
          "com.figma.variableId": "VariableID:2913:9176",
          "com.figma.scopes": [
            "ALL_SCOPES"
          ],
          "com.figma.aliasData": {
            "targetVariableId": "VariableID:76fe14099037e65fc1625e35c130eba49d7cf9fa/-1:-1",
            "targetVariableName": "gold/alphaLight",
            "targetVariableSetId": "VariableCollectionId:83ba552c2f0e2d8b20b04cfcef7f4a43c3163632/-1:-1",
            "targetVariableSetName": "& color hero"
          }
        }
      }
    },
    "error": {
      "error": {
        "$type": "color",
        "$value": {
          "colorSpace": "srgb",
          "components": [
            0.9960784316062927,
            0.7058823704719543,
            0.6941176652908325
          ],
          "alpha": 1,
          "hex": "#FEB4B1"
        },
        "$extensions": {
          "com.figma.variableId": "VariableID:2460:15827",
          "com.figma.scopes": [
            "ALL_SCOPES"
          ],
          "com.figma.aliasData": {
            "targetVariableId": "VariableID:81cac1e0eda67cdbdd91f866b4400142b9d126c2/-1:-1",
            "targetVariableName": "red/80",
            "targetVariableSetId": "VariableCollectionId:83ba552c2f0e2d8b20b04cfcef7f4a43c3163632/-1:-1",
            "targetVariableSetName": "& color hero"
          }
        }
      },
      "errorOverlay": {
        "$type": "color",
        "$value": {
          "colorSpace": "srgb",
          "components": [
            0.9843137264251709,
            0.33725491166114807,
            0.3607843220233917
          ],
          "alpha": 0.18000000715255737,
          "hex": "#FB565C"
        },
        "$extensions": {
          "com.figma.variableId": "VariableID:2460:15828",
          "com.figma.scopes": [
            "ALL_SCOPES"
          ],
          "com.figma.aliasData": {
            "targetVariableId": "VariableID:d002b169d58d84004b233943b91e46b81a625993/-1:-1",
            "targetVariableName": "red/alphaLighter",
            "targetVariableSetId": "VariableCollectionId:83ba552c2f0e2d8b20b04cfcef7f4a43c3163632/-1:-1",
            "targetVariableSetName": "& color hero"
          }
        }
      },
      "errorOverlayHover": {
        "$type": "color",
        "$value": {
          "colorSpace": "srgb",
          "components": [
            0.9843137264251709,
            0.33725491166114807,
            0.3607843220233917
          ],
          "alpha": 0.11999999731779099,
          "hex": "#FB565C"
        },
        "$extensions": {
          "com.figma.variableId": "VariableID:2913:9344",
          "com.figma.scopes": [
            "ALL_SCOPES"
          ],
          "com.figma.aliasData": {
            "targetVariableId": "VariableID:2a69253850ab02cdaad40ab6872750ec0af4066d/-1:-1",
            "targetVariableName": "red/alphaLight",
            "targetVariableSetId": "VariableCollectionId:83ba552c2f0e2d8b20b04cfcef7f4a43c3163632/-1:-1",
            "targetVariableSetName": "& color hero"
          }
        }
      }
    },
    "disabled": {
      "disabled": {
        "$type": "color",
        "$value": {
          "colorSpace": "srgb",
          "components": [
            0.2235294133424759,
            0.22745098173618317,
            0.25882354378700256
          ],
          "alpha": 1,
          "hex": "#393A42"
        },
        "$extensions": {
          "com.figma.variableId": "VariableID:2391:32208",
          "com.figma.scopes": [
            "ALL_SCOPES"
          ],
          "com.figma.aliasData": {
            "targetVariableId": "VariableID:bc37a5dbaa2f73bb7319bff22638f57ca0457d3c/-1:-1",
            "targetVariableName": "cool neutral/25",
            "targetVariableSetId": "VariableCollectionId:83ba552c2f0e2d8b20b04cfcef7f4a43c3163632/-1:-1",
            "targetVariableSetName": "& color hero"
          }
        }
      },
      "disabledInverse": {
        "$type": "color",
        "$value": {
          "colorSpace": "srgb",
          "components": [
            0.6666666865348816,
            0.6666666865348816,
            0.7058823704719543
          ],
          "alpha": 1,
          "hex": "#AAAAB4"
        },
        "$extensions": {
          "com.figma.variableId": "VariableID:2438:9719",
          "com.figma.scopes": [
            "ALL_SCOPES"
          ],
          "com.figma.aliasData": {
            "targetVariableId": "VariableID:482df287abe054ac28a8aab309b119e369d73616/-1:-1",
            "targetVariableName": "cool neutral/70",
            "targetVariableSetId": "VariableCollectionId:83ba552c2f0e2d8b20b04cfcef7f4a43c3163632/-1:-1",
            "targetVariableSetName": "& color hero"
          }
        }
      }
    },
    "surfaces": {
      "canvas": {
        "$type": "color",
        "$value": {
          "colorSpace": "srgb",
          "components": [
            0.07058823853731155,
            0.07450980693101883,
            0.0941176488995552
          ],
          "alpha": 1,
          "hex": "#121318"
        },
        "$extensions": {
          "com.figma.variableId": "VariableID:2353:21996",
          "com.figma.scopes": [
            "ALL_SCOPES"
          ],
          "com.figma.aliasData": {
            "targetVariableId": "VariableID:88e9b3a93ff93a8022b0cadbf0f1b237ea921367/-1:-1",
            "targetVariableName": "cool neutral/6",
            "targetVariableSetId": "VariableCollectionId:83ba552c2f0e2d8b20b04cfcef7f4a43c3163632/-1:-1",
            "targetVariableSetName": "& color hero"
          }
        }
      },
      "container": {
        "$type": "color",
        "$value": {
          "colorSpace": "srgb",
          "components": [
            0.14509804546833038,
            0.14901961386203766,
            0.1764705926179886
          ],
          "alpha": 1,
          "hex": "#25262D"
        },
        "$extensions": {
          "com.figma.variableId": "VariableID:2438:9720",
          "com.figma.scopes": [
            "ALL_SCOPES"
          ],
          "com.figma.aliasData": {
            "targetVariableId": "VariableID:d73cccae738a65c5024bbb7001d9a2919593c260/-1:-1",
            "targetVariableName": "cool neutral/15",
            "targetVariableSetId": "VariableCollectionId:83ba552c2f0e2d8b20b04cfcef7f4a43c3163632/-1:-1",
            "targetVariableSetName": "& color hero"
          }
        }
      },
      "containerPop-windows": {
        "$type": "color",
        "$value": {
          "colorSpace": "srgb",
          "components": [
            0.2235294133424759,
            0.30588236451148987,
            0.8588235378265381
          ],
          "alpha": 0.18000000715255737,
          "hex": "#394EDB"
        },
        "$extensions": {
          "com.figma.variableId": "VariableID:5660:54245",
          "com.figma.scopes": [
            "ALL_SCOPES"
          ],
          "com.figma.aliasData": {
            "targetVariableId": "VariableID:dfa90ee795ca1890dd992eef99407e6ebb5058e7/-1:-1",
            "targetVariableName": "indigo/alphaDarker",
            "targetVariableSetId": "VariableCollectionId:83ba552c2f0e2d8b20b04cfcef7f4a43c3163632/-1:-1",
            "targetVariableSetName": "& color hero"
          }
        }
      },
      "containerPop-web": {
        "$type": "color",
        "$value": {
          "colorSpace": "srgb",
          "components": [
            0.2235294133424759,
            0.30588236451148987,
            0.8588235378265381
          ],
          "alpha": 0.18000000715255737,
          "hex": "#394EDB"
        },
        "$extensions": {
          "com.figma.variableId": "VariableID:5660:54246",
          "com.figma.scopes": [
            "ALL_SCOPES"
          ],
          "com.figma.aliasData": {
            "targetVariableId": "VariableID:dfa90ee795ca1890dd992eef99407e6ebb5058e7/-1:-1",
            "targetVariableName": "indigo/alphaDarker",
            "targetVariableSetId": "VariableCollectionId:83ba552c2f0e2d8b20b04cfcef7f4a43c3163632/-1:-1",
            "targetVariableSetName": "& color hero"
          }
        }
      },
      "container blur": {
        "$type": "color",
        "$value": {
          "colorSpace": "srgb",
          "components": [
            0,
            0,
            0
          ],
          "alpha": 0.699999988079071,
          "hex": "#000000"
        },
        "$extensions": {
          "com.figma.variableId": "VariableID:2743:42431",
          "com.figma.scopes": [
            "ALL_SCOPES"
          ],
          "com.figma.aliasData": {
            "targetVariableId": "VariableID:e81b3125b51934f06bc8182f72adf2ea4073a776/-1:-1",
            "targetVariableName": "black/70a",
            "targetVariableSetId": "VariableCollectionId:83ba552c2f0e2d8b20b04cfcef7f4a43c3163632/-1:-1",
            "targetVariableSetName": "& color hero"
          }
        }
      },
      "container blur high": {
        "$type": "color",
        "$value": {
          "colorSpace": "srgb",
          "components": [
            0,
            0,
            0
          ],
          "alpha": 0.800000011920929,
          "hex": "#000000"
        },
        "$extensions": {
          "com.figma.variableId": "VariableID:2342:22283",
          "com.figma.scopes": [
            "ALL_SCOPES"
          ],
          "com.figma.aliasData": {
            "targetVariableId": "VariableID:1afca4ce7ac67ca1c9e9b2845af1e5cacd14225b/-1:-1",
            "targetVariableName": "black/80a",
            "targetVariableSetId": "VariableCollectionId:83ba552c2f0e2d8b20b04cfcef7f4a43c3163632/-1:-1",
            "targetVariableSetName": "& color hero"
          }
        }
      },
      "onContainer": {
        "$type": "color",
        "$value": {
          "colorSpace": "srgb",
          "components": [
            0.19607843458652496,
            0.18431372940540314,
            0.1882352977991104
          ],
          "alpha": 1,
          "hex": "#322F30"
        },
        "$extensions": {
          "com.figma.variableId": "VariableID:3274:3337",
          "com.figma.scopes": [
            "ALL_SCOPES"
          ],
          "com.figma.aliasData": {
            "targetVariableId": "VariableID:e113764d6880775315fd1503de7a7c316b49a317/-1:-1",
            "targetVariableName": "pure neutral/20",
            "targetVariableSetId": "VariableCollectionId:83ba552c2f0e2d8b20b04cfcef7f4a43c3163632/-1:-1",
            "targetVariableSetName": "& color hero"
          }
        }
      },
      "onContainer low": {
        "$type": "color",
        "$value": {
          "colorSpace": "srgb",
          "components": [
            0.11372549086809158,
            0.10980392247438431,
            0.10980392247438431
          ],
          "alpha": 1,
          "hex": "#1D1C1C"
        },
        "$extensions": {
          "com.figma.variableId": "VariableID:3279:18385",
          "com.figma.scopes": [
            "ALL_SCOPES"
          ],
          "com.figma.aliasData": {
            "targetVariableId": "VariableID:b6271cae64b08c3d46d0ee3c6b5f5f9017bb7b5d/-1:-1",
            "targetVariableName": "pure neutral/10",
            "targetVariableSetId": "VariableCollectionId:83ba552c2f0e2d8b20b04cfcef7f4a43c3163632/-1:-1",
            "targetVariableSetName": "& color hero"
          }
        }
      },
      "onContainer high": {
        "$type": "color",
        "$value": {
          "colorSpace": "srgb",
          "components": [
            0.2666666805744171,
            0.27450981736183167,
            0.30588236451148987
          ],
          "alpha": 1,
          "hex": "#44464E"
        },
        "$extensions": {
          "com.figma.variableId": "VariableID:3279:18386",
          "com.figma.scopes": [
            "ALL_SCOPES"
          ],
          "com.figma.aliasData": {
            "targetVariableId": "VariableID:1d45d231c2f3df5e15ec936c105e2fd81a550a66/-1:-1",
            "targetVariableName": "cool neutral/30",
            "targetVariableSetId": "VariableCollectionId:83ba552c2f0e2d8b20b04cfcef7f4a43c3163632/-1:-1",
            "targetVariableSetName": "& color hero"
          }
        }
      },
      "inverseContainer": {
        "$type": "color",
        "$value": {
          "colorSpace": "srgb",
          "components": [
            0.9764705896377563,
            0.9764705896377563,
            0.9764705896377563
          ],
          "alpha": 1,
          "hex": "#F9F9F9"
        },
        "$extensions": {
          "com.figma.variableId": "VariableID:2390:18067",
          "com.figma.scopes": [
            "ALL_SCOPES"
          ],
          "com.figma.aliasData": {
            "targetVariableId": "VariableID:80a47fb04025c72cb8c10c5d1766baefeea3ed23/-1:-1",
            "targetVariableName": "pure neutral/98",
            "targetVariableSetId": "VariableCollectionId:83ba552c2f0e2d8b20b04cfcef7f4a43c3163632/-1:-1",
            "targetVariableSetName": "& color hero"
          }
        }
      },
      "primary": {
        "$type": "color",
        "$value": {
          "colorSpace": "srgb",
          "components": [
            0.2235294133424759,
            0.30588236451148987,
            0.8588235378265381
          ],
          "alpha": 0.11999999731779099,
          "hex": "#394EDB"
        },
        "$extensions": {
          "com.figma.variableId": "VariableID:2390:18059",
          "com.figma.scopes": [
            "ALL_SCOPES"
          ],
          "com.figma.aliasData": {
            "targetVariableId": "VariableID:5a72fc407eb0d517581ba5fd45feed951f60dfc1/-1:-1",
            "targetVariableName": "indigo/alphaDark",
            "targetVariableSetId": "VariableCollectionId:83ba552c2f0e2d8b20b04cfcef7f4a43c3163632/-1:-1",
            "targetVariableSetName": "& color hero"
          }
        }
      }
    },
    "stroke": {
      "border": {
        "$type": "color",
        "$value": {
          "colorSpace": "srgb",
          "components": [
            0.3686274588108063,
            0.3686274588108063,
            0.3686274588108063
          ],
          "alpha": 1,
          "hex": "#5E5E5E"
        },
        "$extensions": {
          "com.figma.variableId": "VariableID:2390:17568",
          "com.figma.scopes": [
            "ALL_SCOPES"
          ],
          "com.figma.aliasData": {
            "targetVariableId": "VariableID:5c63b76ff6193effea6a0d8a786d0c2745c5aa4e/-1:-1",
            "targetVariableName": "pure neutral/40",
            "targetVariableSetId": "VariableCollectionId:83ba552c2f0e2d8b20b04cfcef7f4a43c3163632/-1:-1",
            "targetVariableSetName": "& color hero"
          }
        }
      },
      "borderPop": {
        "$type": "color",
        "$value": {
          "colorSpace": "srgb",
          "components": [
            0.3686274588108063,
            0.3686274588108063,
            0.3686274588108063
          ],
          "alpha": 1,
          "hex": "#5E5E5E"
        },
        "$extensions": {
          "com.figma.variableId": "VariableID:4306:2105",
          "com.figma.scopes": [
            "ALL_SCOPES"
          ],
          "com.figma.aliasData": {
            "targetVariableId": "VariableID:5c63b76ff6193effea6a0d8a786d0c2745c5aa4e/-1:-1",
            "targetVariableName": "pure neutral/40",
            "targetVariableSetId": "VariableCollectionId:83ba552c2f0e2d8b20b04cfcef7f4a43c3163632/-1:-1",
            "targetVariableSetName": "& color hero"
          }
        }
      },
      "border low": {
        "$type": "color",
        "$value": {
          "colorSpace": "srgb",
          "components": [
            0.19607843458652496,
            0.18431372940540314,
            0.1882352977991104
          ],
          "alpha": 1,
          "hex": "#322F30"
        },
        "$extensions": {
          "com.figma.variableId": "VariableID:2390:17569",
          "com.figma.scopes": [
            "ALL_SCOPES"
          ],
          "com.figma.aliasData": {
            "targetVariableId": "VariableID:e113764d6880775315fd1503de7a7c316b49a317/-1:-1",
            "targetVariableName": "pure neutral/20",
            "targetVariableSetId": "VariableCollectionId:83ba552c2f0e2d8b20b04cfcef7f4a43c3163632/-1:-1",
            "targetVariableSetName": "& color hero"
          }
        }
      },
      "border high": {
        "$type": "color",
        "$value": {
          "colorSpace": "srgb",
          "components": [
            0.46666666865348816,
            0.46666666865348816,
            0.46666666865348816
          ],
          "alpha": 1,
          "hex": "#777777"
        },
        "$extensions": {
          "com.figma.variableId": "VariableID:2475:7226",
          "com.figma.scopes": [
            "ALL_SCOPES"
          ],
          "com.figma.aliasData": {
            "targetVariableId": "VariableID:500b56e846c04755b574c3a58438f3f1470eda6f/-1:-1",
            "targetVariableName": "pure neutral/50",
            "targetVariableSetId": "VariableCollectionId:83ba552c2f0e2d8b20b04cfcef7f4a43c3163632/-1:-1",
            "targetVariableSetName": "& color hero"
          }
        }
      },
      "border container OS": {
        "$type": "color",
        "$value": {
          "colorSpace": "srgb",
          "components": [
            0,
            0,
            0
          ],
          "alpha": 0.05000000074505806,
          "hex": "#000000"
        },
        "$extensions": {
          "com.figma.variableId": "VariableID:2342:22284",
          "com.figma.scopes": [
            "ALL_SCOPES"
          ],
          "com.figma.aliasData": {
            "targetVariableId": "VariableID:e623a2656e4ac8420f010cd6a83943e64025071b/-1:-1",
            "targetVariableName": "black/5a",
            "targetVariableSetId": "VariableCollectionId:83ba552c2f0e2d8b20b04cfcef7f4a43c3163632/-1:-1",
            "targetVariableSetName": "& color hero"
          }
        }
      },
      "border container": {
        "$type": "color",
        "$value": "{&color.stroke.border low}",
        "$extensions": {
          "com.figma.variableId": "VariableID:3848:18202",
          "com.figma.scopes": [
            "ALL_SCOPES"
          ]
        }
      },
      "borderTonalPrimary": {
        "$type": "color",
        "$value": {
          "colorSpace": "srgb",
          "components": [
            0,
            0,
            0
          ],
          "alpha": 1,
          "hex": "#000000"
        },
        "$extensions": {
          "com.figma.variableId": "VariableID:4192:19731",
          "com.figma.scopes": [
            "ALL_SCOPES"
          ],
          "com.figma.aliasData": {
            "targetVariableId": "VariableID:dc6fb23f9341b64255a4df89e08e1d9faa591d9b/-1:-1",
            "targetVariableName": "black/black",
            "targetVariableSetId": "VariableCollectionId:83ba552c2f0e2d8b20b04cfcef7f4a43c3163632/-1:-1",
            "targetVariableSetName": "& color hero"
          }
        }
      }
    },
    "text+icon": {
      "primary": {
        "$type": "color",
        "$value": {
          "colorSpace": "srgb",
          "components": [
            1,
            1,
            1
          ],
          "alpha": 1,
          "hex": "#FFFFFF"
        },
        "$extensions": {
          "com.figma.variableId": "VariableID:2356:22180",
          "com.figma.scopes": [
            "ALL_SCOPES"
          ],
          "com.figma.aliasData": {
            "targetVariableId": "VariableID:f481f844daaac7fae12dab4d7a30ddaff3838e80/-1:-1",
            "targetVariableName": "white/white",
            "targetVariableSetId": "VariableCollectionId:83ba552c2f0e2d8b20b04cfcef7f4a43c3163632/-1:-1",
            "targetVariableSetName": "& color hero"
          }
        }
      },
      "secondary": {
        "$type": "color",
        "$value": {
          "colorSpace": "srgb",
          "components": [
            0.7764706015586853,
            0.7764706015586853,
            0.8117647171020508
          ],
          "alpha": 1,
          "hex": "#C6C6CF"
        },
        "$extensions": {
          "com.figma.variableId": "VariableID:2356:22181",
          "com.figma.scopes": [
            "ALL_SCOPES"
          ],
          "com.figma.aliasData": {
            "targetVariableId": "VariableID:a63c223348290db6fa72423f12dd3da668ac5ef1/-1:-1",
            "targetVariableName": "cool neutral/80",
            "targetVariableSetId": "VariableCollectionId:83ba552c2f0e2d8b20b04cfcef7f4a43c3163632/-1:-1",
            "targetVariableSetName": "& color hero"
          }
        }
      },
      "placeholder": {
        "$type": "color",
        "$value": {
          "colorSpace": "srgb",
          "components": [
            0.6666666865348816,
            0.6666666865348816,
            0.7058823704719543
          ],
          "alpha": 1,
          "hex": "#AAAAB4"
        },
        "$extensions": {
          "com.figma.variableId": "VariableID:3515:49761",
          "com.figma.scopes": [
            "ALL_SCOPES"
          ],
          "com.figma.aliasData": {
            "targetVariableId": "VariableID:482df287abe054ac28a8aab309b119e369d73616/-1:-1",
            "targetVariableName": "cool neutral/70",
            "targetVariableSetId": "VariableCollectionId:83ba552c2f0e2d8b20b04cfcef7f4a43c3163632/-1:-1",
            "targetVariableSetName": "& color hero"
          }
        }
      },
      "inverse": {
        "$type": "color",
        "$value": {
          "colorSpace": "srgb",
          "components": [
            0.14509804546833038,
            0.14901961386203766,
            0.1764705926179886
          ],
          "alpha": 1,
          "hex": "#25262D"
        },
        "$extensions": {
          "com.figma.variableId": "VariableID:2390:18068",
          "com.figma.scopes": [
            "ALL_SCOPES"
          ],
          "com.figma.aliasData": {
            "targetVariableId": "VariableID:d73cccae738a65c5024bbb7001d9a2919593c260/-1:-1",
            "targetVariableName": "cool neutral/15",
            "targetVariableSetId": "VariableCollectionId:83ba552c2f0e2d8b20b04cfcef7f4a43c3163632/-1:-1",
            "targetVariableSetName": "& color hero"
          }
        }
      },
      "onPrimary": {
        "$type": "color",
        "$value": {
          "colorSpace": "srgb",
          "components": [
            0.07450980693101883,
            0.13725490868091583,
            0.5176470875740051
          ],
          "alpha": 1,
          "hex": "#132384"
        },
        "$extensions": {
          "com.figma.variableId": "VariableID:2391:32205",
          "com.figma.scopes": [
            "ALL_SCOPES"
          ],
          "com.figma.aliasData": {
            "targetVariableId": "VariableID:5704a58b8ab3e99dfa8dc227f23271f0fa795c86/-1:-1",
            "targetVariableName": "indigo/20",
            "targetVariableSetId": "VariableCollectionId:83ba552c2f0e2d8b20b04cfcef7f4a43c3163632/-1:-1",
            "targetVariableSetName": "& color hero"
          }
        }
      },
      "onSecondary": {
        "$type": "color",
        "$value": {
          "colorSpace": "srgb",
          "components": [
            0.14509804546833038,
            0.14901961386203766,
            0.1764705926179886
          ],
          "alpha": 1,
          "hex": "#25262D"
        },
        "$extensions": {
          "com.figma.variableId": "VariableID:5004:15216",
          "com.figma.scopes": [
            "ALL_SCOPES"
          ],
          "com.figma.aliasData": {
            "targetVariableId": "VariableID:d73cccae738a65c5024bbb7001d9a2919593c260/-1:-1",
            "targetVariableName": "cool neutral/15",
            "targetVariableSetId": "VariableCollectionId:83ba552c2f0e2d8b20b04cfcef7f4a43c3163632/-1:-1",
            "targetVariableSetName": "& color hero"
          }
        }
      },
      "onPrimary disabled": {
        "$type": "color",
        "$value": {
          "colorSpace": "srgb",
          "components": [
            0.07450980693101883,
            0.13725490868091583,
            0.5176470875740051
          ],
          "alpha": 1,
          "hex": "#132384"
        },
        "$extensions": {
          "com.figma.variableId": "VariableID:2391:32209",
          "com.figma.scopes": [
            "ALL_SCOPES"
          ],
          "com.figma.aliasData": {
            "targetVariableId": "VariableID:5704a58b8ab3e99dfa8dc227f23271f0fa795c86/-1:-1",
            "targetVariableName": "indigo/20",
            "targetVariableSetId": "VariableCollectionId:83ba552c2f0e2d8b20b04cfcef7f4a43c3163632/-1:-1",
            "targetVariableSetName": "& color hero"
          }
        }
      },
      "onTonal": {
        "$type": "color",
        "$value": {
          "colorSpace": "srgb",
          "components": [
            0.8039215803146362,
            0.8196078538894653,
            1
          ],
          "alpha": 1,
          "hex": "#CDD1FF"
        },
        "$extensions": {
          "com.figma.variableId": "VariableID:3861:4958",
          "com.figma.scopes": [
            "ALL_SCOPES"
          ],
          "com.figma.aliasData": {
            "targetVariableId": "VariableID:1dc3a9d7f11df2193d8809e4d02e4e4dcb2d86ba/-1:-1",
            "targetVariableName": "indigo/85",
            "targetVariableSetId": "VariableCollectionId:83ba552c2f0e2d8b20b04cfcef7f4a43c3163632/-1:-1",
            "targetVariableSetName": "& color hero"
          }
        }
      },
      "onTonalInverse": {
        "$type": "color",
        "$value": {
          "colorSpace": "srgb",
          "components": [
            0.8705882430076599,
            0.8784313797950745,
            1
          ],
          "alpha": 1,
          "hex": "#DEE0FF"
        },
        "$extensions": {
          "com.figma.variableId": "VariableID:5164:18642",
          "com.figma.scopes": [
            "ALL_SCOPES"
          ],
          "com.figma.aliasData": {
            "targetVariableId": "VariableID:2de74d9c663d70e1a4fd12f96f7626116274507f/-1:-1",
            "targetVariableName": "indigo/90",
            "targetVariableSetId": "VariableCollectionId:83ba552c2f0e2d8b20b04cfcef7f4a43c3163632/-1:-1",
            "targetVariableSetName": "& color hero"
          }
        }
      },
      "onTonalSecondary": {
        "$type": "color",
        "$value": {
          "colorSpace": "srgb",
          "components": [
            1,
            1,
            1
          ],
          "alpha": 1,
          "hex": "#FFFFFF"
        },
        "$extensions": {
          "com.figma.variableId": "VariableID:4116:5252",
          "com.figma.scopes": [
            "ALL_SCOPES"
          ],
          "com.figma.aliasData": {
            "targetVariableId": "VariableID:f481f844daaac7fae12dab4d7a30ddaff3838e80/-1:-1",
            "targetVariableName": "white/white",
            "targetVariableSetId": "VariableCollectionId:83ba552c2f0e2d8b20b04cfcef7f4a43c3163632/-1:-1",
            "targetVariableSetName": "& color hero"
          }
        }
      }
    },
    "elevation": {
      "drop-shadow-light": {
        "$type": "color",
        "$value": {
          "colorSpace": "srgb",
          "components": [
            0,
            0,
            0
          ],
          "alpha": 0.20000000298023224,
          "hex": "#000000"
        },
        "$extensions": {
          "com.figma.variableId": "VariableID:2339:23984",
          "com.figma.scopes": [
            "ALL_SCOPES"
          ],
          "com.figma.aliasData": {
            "targetVariableId": "VariableID:709cbe9210577cc560dc64c3ea5e5c24665b255a/-1:-1",
            "targetVariableName": "black/20a",
            "targetVariableSetId": "VariableCollectionId:83ba552c2f0e2d8b20b04cfcef7f4a43c3163632/-1:-1",
            "targetVariableSetName": "& color hero"
          }
        }
      },
      "drop-shadow-heavy": {
        "$type": "color",
        "$value": {
          "colorSpace": "srgb",
          "components": [
            0,
            0,
            0
          ],
          "alpha": 0.25,
          "hex": "#000000"
        },
        "$extensions": {
          "com.figma.variableId": "VariableID:2339:23982",
          "com.figma.scopes": [
            "ALL_SCOPES"
          ],
          "com.figma.aliasData": {
            "targetVariableId": "VariableID:27747aeea87c2526711f0e6e64e4bf2f3c04cacd/-1:-1",
            "targetVariableName": "black/25a",
            "targetVariableSetId": "VariableCollectionId:83ba552c2f0e2d8b20b04cfcef7f4a43c3163632/-1:-1",
            "targetVariableSetName": "& color hero"
          }
        }
      }
    },
    "overlay": {
      "scrim": {
        "$type": "color",
        "$value": {
          "colorSpace": "srgb",
          "components": [
            0,
            0,
            0
          ],
          "alpha": 0.30000001192092896,
          "hex": "#000000"
        },
        "$extensions": {
          "com.figma.variableId": "VariableID:3677:2080",
          "com.figma.scopes": [
            "ALL_SCOPES"
          ],
          "com.figma.aliasData": {
            "targetVariableId": "VariableID:b80304a336dc31eca8b3897eb9b77d65d6444465/-1:-1",
            "targetVariableName": "black/30a",
            "targetVariableSetId": "VariableCollectionId:83ba552c2f0e2d8b20b04cfcef7f4a43c3163632/-1:-1",
            "targetVariableSetName": "& color hero"
          }
        }
      }
    },
    "badge": {
      "red": {
        "$type": "color",
        "$value": {
          "colorSpace": "srgb",
          "components": [
            0.9960784316062927,
            0.7058823704719543,
            0.6941176652908325
          ],
          "alpha": 1,
          "hex": "#FEB4B1"
        },
        "$extensions": {
          "com.figma.variableId": "VariableID:4303:1124",
          "com.figma.scopes": [
            "ALL_SCOPES"
          ],
          "com.figma.aliasData": {
            "targetVariableId": "VariableID:81cac1e0eda67cdbdd91f866b4400142b9d126c2/-1:-1",
            "targetVariableName": "red/80",
            "targetVariableSetId": "VariableCollectionId:83ba552c2f0e2d8b20b04cfcef7f4a43c3163632/-1:-1",
            "targetVariableSetName": "& color hero"
          }
        }
      },
      "redLight": {
        "$type": "color",
        "$value": {
          "colorSpace": "srgb",
          "components": [
            0.9843137264251709,
            0.33725491166114807,
            0.3607843220233917
          ],
          "alpha": 0.18000000715255737,
          "hex": "#FB565C"
        },
        "$extensions": {
          "com.figma.variableId": "VariableID:4304:1178",
          "com.figma.scopes": [
            "ALL_SCOPES"
          ],
          "com.figma.aliasData": {
            "targetVariableId": "VariableID:d002b169d58d84004b233943b91e46b81a625993/-1:-1",
            "targetVariableName": "red/alphaLighter",
            "targetVariableSetId": "VariableCollectionId:83ba552c2f0e2d8b20b04cfcef7f4a43c3163632/-1:-1",
            "targetVariableSetName": "& color hero"
          }
        }
      },
      "text + icon onRedLight": {
        "$type": "color",
        "$value": {
          "colorSpace": "srgb",
          "components": [
            0.9960784316062927,
            0.7058823704719543,
            0.6941176652908325
          ],
          "alpha": 1,
          "hex": "#FEB4B1"
        },
        "$extensions": {
          "com.figma.variableId": "VariableID:4304:1180",
          "com.figma.scopes": [
            "ALL_SCOPES"
          ],
          "com.figma.aliasData": {
            "targetVariableId": "VariableID:81cac1e0eda67cdbdd91f866b4400142b9d126c2/-1:-1",
            "targetVariableName": "red/80",
            "targetVariableSetId": "VariableCollectionId:83ba552c2f0e2d8b20b04cfcef7f4a43c3163632/-1:-1",
            "targetVariableSetName": "& color hero"
          }
        }
      },
      "orange": {
        "$type": "color",
        "$value": {
          "colorSpace": "srgb",
          "components": [
            1,
            0.7098039388656616,
            0.6000000238418579
          ],
          "alpha": 1,
          "hex": "#FFB599"
        },
        "$extensions": {
          "com.figma.variableId": "VariableID:4304:1154",
          "com.figma.scopes": [
            "ALL_SCOPES"
          ],
          "com.figma.aliasData": {
            "targetVariableId": "VariableID:741debf104cc697addcddd2e02f0df2654833bbd/-1:-1",
            "targetVariableName": "orange/80",
            "targetVariableSetId": "VariableCollectionId:83ba552c2f0e2d8b20b04cfcef7f4a43c3163632/-1:-1",
            "targetVariableSetName": "& color hero"
          }
        }
      },
      "orangeLight": {
        "$type": "color",
        "$value": {
          "colorSpace": "srgb",
          "components": [
            0.9529411792755127,
            0.3921568691730499,
            0.125490203499794
          ],
          "alpha": 0.18000000715255737,
          "hex": "#F36420"
        },
        "$extensions": {
          "com.figma.variableId": "VariableID:4304:1179",
          "com.figma.scopes": [
            "ALL_SCOPES"
          ],
          "com.figma.aliasData": {
            "targetVariableId": "VariableID:6c88224ff2be0b5ef97329bf9d5a511bd6207350/-1:-1",
            "targetVariableName": "orange/alphaLighter",
            "targetVariableSetId": "VariableCollectionId:83ba552c2f0e2d8b20b04cfcef7f4a43c3163632/-1:-1",
            "targetVariableSetName": "& color hero"
          }
        }
      },
      "text + icon onOrangeLight": {
        "$type": "color",
        "$value": {
          "colorSpace": "srgb",
          "components": [
            1,
            0.7098039388656616,
            0.6000000238418579
          ],
          "alpha": 1,
          "hex": "#FFB599"
        },
        "$extensions": {
          "com.figma.variableId": "VariableID:4304:1181",
          "com.figma.scopes": [
            "ALL_SCOPES"
          ],
          "com.figma.aliasData": {
            "targetVariableId": "VariableID:741debf104cc697addcddd2e02f0df2654833bbd/-1:-1",
            "targetVariableName": "orange/80",
            "targetVariableSetId": "VariableCollectionId:83ba552c2f0e2d8b20b04cfcef7f4a43c3163632/-1:-1",
            "targetVariableSetName": "& color hero"
          }
        }
      },
      "amber": {
        "$type": "color",
        "$value": {
          "colorSpace": "srgb",
          "components": [
            1,
            0.7176470756530762,
            0.4745098054409027
          ],
          "alpha": 1,
          "hex": "#FFB779"
        },
        "$extensions": {
          "com.figma.variableId": "VariableID:4304:1155",
          "com.figma.scopes": [
            "ALL_SCOPES"
          ],
          "com.figma.aliasData": {
            "targetVariableId": "VariableID:1160a9458840df8b347e3b5642393e6c9e5e794f/-1:-1",
            "targetVariableName": "amber/80",
            "targetVariableSetId": "VariableCollectionId:83ba552c2f0e2d8b20b04cfcef7f4a43c3163632/-1:-1",
            "targetVariableSetName": "& color hero"
          }
        }
      },
      "amberLight": {
        "$type": "color",
        "$value": {
          "colorSpace": "srgb",
          "components": [
            1,
            0.7176470756530762,
            0.4745098054409027
          ],
          "alpha": 0.18000000715255737,
          "hex": "#FFB779"
        },
        "$extensions": {
          "com.figma.variableId": "VariableID:4304:1182",
          "com.figma.scopes": [
            "ALL_SCOPES"
          ],
          "com.figma.aliasData": {
            "targetVariableId": "VariableID:ffb5883b1c94ef2e0fbd92211207d94c877c318b/-1:-1",
            "targetVariableName": "amber/alphaLighter",
            "targetVariableSetId": "VariableCollectionId:83ba552c2f0e2d8b20b04cfcef7f4a43c3163632/-1:-1",
            "targetVariableSetName": "& color hero"
          }
        }
      },
      "text + icon onAmberLight": {
        "$type": "color",
        "$value": {
          "colorSpace": "srgb",
          "components": [
            1,
            0.7176470756530762,
            0.4745098054409027
          ],
          "alpha": 1,
          "hex": "#FFB779"
        },
        "$extensions": {
          "com.figma.variableId": "VariableID:4304:1183",
          "com.figma.scopes": [
            "ALL_SCOPES"
          ],
          "com.figma.aliasData": {
            "targetVariableId": "VariableID:1160a9458840df8b347e3b5642393e6c9e5e794f/-1:-1",
            "targetVariableName": "amber/80",
            "targetVariableSetId": "VariableCollectionId:83ba552c2f0e2d8b20b04cfcef7f4a43c3163632/-1:-1",
            "targetVariableSetName": "& color hero"
          }
        }
      },
      "gold": {
        "$type": "color",
        "$value": {
          "colorSpace": "srgb",
          "components": [
            0.9882352948188782,
            0.7333333492279053,
            0.25882354378700256
          ],
          "alpha": 1,
          "hex": "#FCBB42"
        },
        "$extensions": {
          "com.figma.variableId": "VariableID:4304:1156",
          "com.figma.scopes": [
            "ALL_SCOPES"
          ],
          "com.figma.aliasData": {
            "targetVariableId": "VariableID:219d1f21bcb3e45c16cdf8c0227f90ce0edd8614/-1:-1",
            "targetVariableName": "gold/80",
            "targetVariableSetId": "VariableCollectionId:83ba552c2f0e2d8b20b04cfcef7f4a43c3163632/-1:-1",
            "targetVariableSetName": "& color hero"
          }
        }
      },
      "goldLight": {
        "$type": "color",
        "$value": {
          "colorSpace": "srgb",
          "components": [
            0.9882352948188782,
            0.7333333492279053,
            0.25882354378700256
          ],
          "alpha": 0.18000000715255737,
          "hex": "#FCBB42"
        },
        "$extensions": {
          "com.figma.variableId": "VariableID:4304:1449",
          "com.figma.scopes": [
            "ALL_SCOPES"
          ],
          "com.figma.aliasData": {
            "targetVariableId": "VariableID:32b856343b982d81b03291d6e686e5711aad33d2/-1:-1",
            "targetVariableName": "gold/alphaLighter",
            "targetVariableSetId": "VariableCollectionId:83ba552c2f0e2d8b20b04cfcef7f4a43c3163632/-1:-1",
            "targetVariableSetName": "& color hero"
          }
        }
      },
      "text + icon onGoldLight": {
        "$type": "color",
        "$value": {
          "colorSpace": "srgb",
          "components": [
            1,
            0.8666666746139526,
            0.6666666865348816
          ],
          "alpha": 1,
          "hex": "#FFDDAA"
        },
        "$extensions": {
          "com.figma.variableId": "VariableID:4304:1450",
          "com.figma.scopes": [
            "ALL_SCOPES"
          ],
          "com.figma.aliasData": {
            "targetVariableId": "VariableID:13a843155fe53b0db2686101e59b3cf8d34cd84d/-1:-1",
            "targetVariableName": "gold/90",
            "targetVariableSetId": "VariableCollectionId:83ba552c2f0e2d8b20b04cfcef7f4a43c3163632/-1:-1",
            "targetVariableSetName": "& color hero"
          }
        }
      },
      "yellow": {
        "$type": "color",
        "$value": {
          "colorSpace": "srgb",
          "components": [
            0.886274516582489,
            0.7764706015586853,
            0
          ],
          "alpha": 1,
          "hex": "#E2C600"
        },
        "$extensions": {
          "com.figma.variableId": "VariableID:4304:1157",
          "com.figma.scopes": [
            "ALL_SCOPES"
          ],
          "com.figma.aliasData": {
            "targetVariableId": "VariableID:85c6a5bb1c7f474572e6ab8f74b892925802e79c/-1:-1",
            "targetVariableName": "yellow/80",
            "targetVariableSetId": "VariableCollectionId:83ba552c2f0e2d8b20b04cfcef7f4a43c3163632/-1:-1",
            "targetVariableSetName": "& color hero"
          }
        }
      },
      "yellowLight": {
        "$type": "color",
        "$value": {
          "colorSpace": "srgb",
          "components": [
            0.886274516582489,
            0.7764706015586853,
            0
          ],
          "alpha": 0.18000000715255737,
          "hex": "#E2C600"
        },
        "$extensions": {
          "com.figma.variableId": "VariableID:4304:1453",
          "com.figma.scopes": [
            "ALL_SCOPES"
          ],
          "com.figma.aliasData": {
            "targetVariableId": "VariableID:0431e1f656629704154c8c73d56657276a90c19b/-1:-1",
            "targetVariableName": "yellow/alphaLighter",
            "targetVariableSetId": "VariableCollectionId:83ba552c2f0e2d8b20b04cfcef7f4a43c3163632/-1:-1",
            "targetVariableSetName": "& color hero"
          }
        }
      },
      "text + icon onYellowLight": {
        "$type": "color",
        "$value": {
          "colorSpace": "srgb",
          "components": [
            0.9764705896377563,
            0.8901960849761963,
            0.45490196347236633
          ],
          "alpha": 1,
          "hex": "#F9E374"
        },
        "$extensions": {
          "com.figma.variableId": "VariableID:4304:1454",
          "com.figma.scopes": [
            "ALL_SCOPES"
          ],
          "com.figma.aliasData": {
            "targetVariableId": "VariableID:d9db9e2ecbcfc3268a6cb66fe4895101a5154329/-1:-1",
            "targetVariableName": "yellow/90",
            "targetVariableSetId": "VariableCollectionId:83ba552c2f0e2d8b20b04cfcef7f4a43c3163632/-1:-1",
            "targetVariableSetName": "& color hero"
          }
        }
      },
      "lime": {
        "$type": "color",
        "$value": {
          "colorSpace": "srgb",
          "components": [
            0.7254902124404907,
            0.8235294222831726,
            0.21568627655506134
          ],
          "alpha": 1,
          "hex": "#B9D237"
        },
        "$extensions": {
          "com.figma.variableId": "VariableID:4304:1165",
          "com.figma.scopes": [
            "ALL_SCOPES"
          ],
          "com.figma.aliasData": {
            "targetVariableId": "VariableID:7aa58b46e4a42a162eea4bd394dba15912586281/-1:-1",
            "targetVariableName": "lime/80",
            "targetVariableSetId": "VariableCollectionId:83ba552c2f0e2d8b20b04cfcef7f4a43c3163632/-1:-1",
            "targetVariableSetName": "& color hero"
          }
        }
      },
      "limeLight": {
        "$type": "color",
        "$value": {
          "colorSpace": "srgb",
          "components": [
            0.7254902124404907,
            0.8235294222831726,
            0.21568627655506134
          ],
          "alpha": 0.18000000715255737,
          "hex": "#B9D237"
        },
        "$extensions": {
          "com.figma.variableId": "VariableID:4306:1363",
          "com.figma.scopes": [
            "ALL_SCOPES"
          ],
          "com.figma.aliasData": {
            "targetVariableId": "VariableID:eb7203da48097a5ac1bbd018136431cb1e670e7f/-1:-1",
            "targetVariableName": "lime/alphaLighter",
            "targetVariableSetId": "VariableCollectionId:83ba552c2f0e2d8b20b04cfcef7f4a43c3163632/-1:-1",
            "targetVariableSetName": "& color hero"
          }
        }
      },
      "text + icon onLimeLight": {
        "$type": "color",
        "$value": {
          "colorSpace": "srgb",
          "components": [
            0.8470588326454163,
            0.9254902005195618,
            0.48235294222831726
          ],
          "alpha": 1,
          "hex": "#D8EC7B"
        },
        "$extensions": {
          "com.figma.variableId": "VariableID:4306:1364",
          "com.figma.scopes": [
            "ALL_SCOPES"
          ],
          "com.figma.aliasData": {
            "targetVariableId": "VariableID:4d906725efec15737ff2c4fd311585e4affb85b9/-1:-1",
            "targetVariableName": "lime/90",
            "targetVariableSetId": "VariableCollectionId:83ba552c2f0e2d8b20b04cfcef7f4a43c3163632/-1:-1",
            "targetVariableSetName": "& color hero"
          }
        }
      },
      "green": {
        "$type": "color",
        "$value": {
          "colorSpace": "srgb",
          "components": [
            0.5176470875740051,
            0.8588235378265381,
            0.3960784375667572
          ],
          "alpha": 1,
          "hex": "#84DB65"
        },
        "$extensions": {
          "com.figma.variableId": "VariableID:4304:1166",
          "com.figma.scopes": [
            "ALL_SCOPES"
          ],
          "com.figma.aliasData": {
            "targetVariableId": "VariableID:17ddffd386fcd108040e483806c25106d0bc3aeb/-1:-1",
            "targetVariableName": "green/80",
            "targetVariableSetId": "VariableCollectionId:83ba552c2f0e2d8b20b04cfcef7f4a43c3163632/-1:-1",
            "targetVariableSetName": "& color hero"
          }
        }
      },
      "greenLight": {
        "$type": "color",
        "$value": {
          "colorSpace": "srgb",
          "components": [
            0.29019609093666077,
            0.6431372761726379,
            0.1725490242242813
          ],
          "alpha": 0.18000000715255737,
          "hex": "#4AA42C"
        },
        "$extensions": {
          "com.figma.variableId": "VariableID:4306:1365",
          "com.figma.scopes": [
            "ALL_SCOPES"
          ],
          "com.figma.aliasData": {
            "targetVariableId": "VariableID:af95a3261d281ccb0b96b48e66c24453c0857171/-1:-1",
            "targetVariableName": "green/alphaLighter",
            "targetVariableSetId": "VariableCollectionId:83ba552c2f0e2d8b20b04cfcef7f4a43c3163632/-1:-1",
            "targetVariableSetName": "& color hero"
          }
        }
      },
      "text + icon onGreenLight": {
        "$type": "color",
        "$value": {
          "colorSpace": "srgb",
          "components": [
            0.7215686440467834,
            0.9529411792755127,
            0.615686297416687
          ],
          "alpha": 1,
          "hex": "#B8F39D"
        },
        "$extensions": {
          "com.figma.variableId": "VariableID:4306:1366",
          "com.figma.scopes": [
            "ALL_SCOPES"
          ],
          "com.figma.aliasData": {
            "targetVariableId": "VariableID:4ec23865f099a8bd1bb336944acd970e02b18963/-1:-1",
            "targetVariableName": "green/90",
            "targetVariableSetId": "VariableCollectionId:83ba552c2f0e2d8b20b04cfcef7f4a43c3163632/-1:-1",
            "targetVariableSetName": "& color hero"
          }
        }
      },
      "jade": {
        "$type": "color",
        "$value": {
          "colorSpace": "srgb",
          "components": [
            0.2666666805744171,
            0.8745098114013672,
            0.5843137502670288
          ],
          "alpha": 1,
          "hex": "#44DF95"
        },
        "$extensions": {
          "com.figma.variableId": "VariableID:4304:1167",
          "com.figma.scopes": [
            "ALL_SCOPES"
          ],
          "com.figma.aliasData": {
            "targetVariableId": "VariableID:0777b84940b616ec8a2defebf882a2cc2627a13a/-1:-1",
            "targetVariableName": "jade/80",
            "targetVariableSetId": "VariableCollectionId:83ba552c2f0e2d8b20b04cfcef7f4a43c3163632/-1:-1",
            "targetVariableSetName": "& color hero"
          }
        }
      },
      "jadeLight": {
        "$type": "color",
        "$value": {
          "colorSpace": "srgb",
          "components": [
            0.2666666805744171,
            0.8745098114013672,
            0.5843137502670288
          ],
          "alpha": 0.18000000715255737,
          "hex": "#44DF95"
        },
        "$extensions": {
          "com.figma.variableId": "VariableID:4306:1367",
          "com.figma.scopes": [
            "ALL_SCOPES"
          ],
          "com.figma.aliasData": {
            "targetVariableId": "VariableID:a4b2c37c2ee722c247fe755595abec9454f9a3a4/-1:-1",
            "targetVariableName": "jade/alphaLighter",
            "targetVariableSetId": "VariableCollectionId:83ba552c2f0e2d8b20b04cfcef7f4a43c3163632/-1:-1",
            "targetVariableSetName": "& color hero"
          }
        }
      },
      "text + icon onJadeLight": {
        "$type": "color",
        "$value": {
          "colorSpace": "srgb",
          "components": [
            0.6196078658103943,
            0.95686274766922,
            0.7490196228027344
          ],
          "alpha": 1,
          "hex": "#9EF4BF"
        },
        "$extensions": {
          "com.figma.variableId": "VariableID:4306:1368",
          "com.figma.scopes": [
            "ALL_SCOPES"
          ],
          "com.figma.aliasData": {
            "targetVariableId": "VariableID:d33c46828fd425f53124282954ebd1b7f679edc1/-1:-1",
            "targetVariableName": "jade/90",
            "targetVariableSetId": "VariableCollectionId:83ba552c2f0e2d8b20b04cfcef7f4a43c3163632/-1:-1",
            "targetVariableSetName": "& color hero"
          }
        }
      },
      "teal": {
        "$type": "color",
        "$value": {
          "colorSpace": "srgb",
          "components": [
            0,
            0.8745098114013672,
            0.7529411911964417
          ],
          "alpha": 1,
          "hex": "#00DFC0"
        },
        "$extensions": {
          "com.figma.variableId": "VariableID:4304:1168",
          "com.figma.scopes": [
            "ALL_SCOPES"
          ],
          "com.figma.aliasData": {
            "targetVariableId": "VariableID:d4237af53be0650a857998e51155637a634d9895/-1:-1",
            "targetVariableName": "teal/80",
            "targetVariableSetId": "VariableCollectionId:83ba552c2f0e2d8b20b04cfcef7f4a43c3163632/-1:-1",
            "targetVariableSetName": "& color hero"
          }
        }
      },
      "tealLight": {
        "$type": "color",
        "$value": {
          "colorSpace": "srgb",
          "components": [
            0,
            0.8745098114013672,
            0.7529411911964417
          ],
          "alpha": 0.18000000715255737,
          "hex": "#00DFC0"
        },
        "$extensions": {
          "com.figma.variableId": "VariableID:4306:1369",
          "com.figma.scopes": [
            "ALL_SCOPES"
          ],
          "com.figma.aliasData": {
            "targetVariableId": "VariableID:7b35f3f57e02effc7aa4c20361c444f68a9cc5dc/-1:-1",
            "targetVariableName": "teal/alphaLighter",
            "targetVariableSetId": "VariableCollectionId:83ba552c2f0e2d8b20b04cfcef7f4a43c3163632/-1:-1",
            "targetVariableSetName": "& color hero"
          }
        }
      },
      "text + icon onTealLight": {
        "$type": "color",
        "$value": {
          "colorSpace": "srgb",
          "components": [
            0.5960784554481506,
            0.95686274766922,
            0.8705882430076599
          ],
          "alpha": 1,
          "hex": "#98F4DE"
        },
        "$extensions": {
          "com.figma.variableId": "VariableID:4306:1370",
          "com.figma.scopes": [
            "ALL_SCOPES"
          ],
          "com.figma.aliasData": {
            "targetVariableId": "VariableID:835656e107dfacbde85cfe3ea97cbbf386e7c43f/-1:-1",
            "targetVariableName": "teal/90",
            "targetVariableSetId": "VariableCollectionId:83ba552c2f0e2d8b20b04cfcef7f4a43c3163632/-1:-1",
            "targetVariableSetName": "& color hero"
          }
        }
      },
      "aqua": {
        "$type": "color",
        "$value": {
          "colorSpace": "srgb",
          "components": [
            0,
            0.8627451062202454,
            0.886274516582489
          ],
          "alpha": 1,
          "hex": "#00DCE2"
        },
        "$extensions": {
          "com.figma.variableId": "VariableID:4304:1169",
          "com.figma.scopes": [
            "ALL_SCOPES"
          ],
          "com.figma.aliasData": {
            "targetVariableId": "VariableID:593cc590f95585a4e21b32934c39a6b1980bf8b4/-1:-1",
            "targetVariableName": "aqua/80",
            "targetVariableSetId": "VariableCollectionId:83ba552c2f0e2d8b20b04cfcef7f4a43c3163632/-1:-1",
            "targetVariableSetName": "& color hero"
          }
        }
      },
      "aquaLight": {
        "$type": "color",
        "$value": {
          "colorSpace": "srgb",
          "components": [
            0,
            0.8627451062202454,
            0.886274516582489
          ],
          "alpha": 0.18000000715255737,
          "hex": "#00DCE2"
        },
        "$extensions": {
          "com.figma.variableId": "VariableID:4306:1372",
          "com.figma.scopes": [
            "ALL_SCOPES"
          ],
          "com.figma.aliasData": {
            "targetVariableId": "VariableID:664fda91dd7ddc120a641c954af7cabb4a42124a/-1:-1",
            "targetVariableName": "aqua/alphaLighter",
            "targetVariableSetId": "VariableCollectionId:83ba552c2f0e2d8b20b04cfcef7f4a43c3163632/-1:-1",
            "targetVariableSetName": "& color hero"
          }
        }
      },
      "text + icon onAquaLight": {
        "$type": "color",
        "$value": {
          "colorSpace": "srgb",
          "components": [
            0.6235294342041016,
            0.9411764740943909,
            0.9529411792755127
          ],
          "alpha": 1,
          "hex": "#9FF0F3"
        },
        "$extensions": {
          "com.figma.variableId": "VariableID:4306:1373",
          "com.figma.scopes": [
            "ALL_SCOPES"
          ],
          "com.figma.aliasData": {
            "targetVariableId": "VariableID:aef41eaa208387653c1225ac0cf141a1c7ffaad9/-1:-1",
            "targetVariableName": "aqua/90",
            "targetVariableSetId": "VariableCollectionId:83ba552c2f0e2d8b20b04cfcef7f4a43c3163632/-1:-1",
            "targetVariableSetName": "& color hero"
          }
        }
      },
      "cyan": {
        "$type": "color",
        "$value": {
          "colorSpace": "srgb",
          "components": [
            0.30980393290519714,
            0.8392156958580017,
            0.9803921580314636
          ],
          "alpha": 1,
          "hex": "#4FD6FA"
        },
        "$extensions": {
          "com.figma.variableId": "VariableID:4304:1170",
          "com.figma.scopes": [
            "ALL_SCOPES"
          ],
          "com.figma.aliasData": {
            "targetVariableId": "VariableID:accf2d6adf4ff3d0d309e529c29250b1c5a988f6/-1:-1",
            "targetVariableName": "cyan/80",
            "targetVariableSetId": "VariableCollectionId:83ba552c2f0e2d8b20b04cfcef7f4a43c3163632/-1:-1",
            "targetVariableSetName": "& color hero"
          }
        }
      },
      "cyanLight": {
        "$type": "color",
        "$value": {
          "colorSpace": "srgb",
          "components": [
            0.30980393290519714,
            0.8392156958580017,
            0.9803921580314636
          ],
          "alpha": 0.18000000715255737,
          "hex": "#4FD6FA"
        },
        "$extensions": {
          "com.figma.variableId": "VariableID:4306:1376",
          "com.figma.scopes": [
            "ALL_SCOPES"
          ],
          "com.figma.aliasData": {
            "targetVariableId": "VariableID:bc6a52e31496ad516891065e797549e3c30be262/-1:-1",
            "targetVariableName": "cyan/alphaLighter",
            "targetVariableSetId": "VariableCollectionId:83ba552c2f0e2d8b20b04cfcef7f4a43c3163632/-1:-1",
            "targetVariableSetName": "& color hero"
          }
        }
      },
      "text + icon onCyanLight": {
        "$type": "color",
        "$value": {
          "colorSpace": "srgb",
          "components": [
            0.7176470756530762,
            0.9215686321258545,
            0.9882352948188782
          ],
          "alpha": 1,
          "hex": "#B7EBFC"
        },
        "$extensions": {
          "com.figma.variableId": "VariableID:4306:1377",
          "com.figma.scopes": [
            "ALL_SCOPES"
          ],
          "com.figma.aliasData": {
            "targetVariableId": "VariableID:cc3919b282e7d995c0685d87aebef70cbb1d60b7/-1:-1",
            "targetVariableName": "cyan/90",
            "targetVariableSetId": "VariableCollectionId:83ba552c2f0e2d8b20b04cfcef7f4a43c3163632/-1:-1",
            "targetVariableSetName": "& color hero"
          }
        }
      },
      "azure": {
        "$type": "color",
        "$value": {
          "colorSpace": "srgb",
          "components": [
            0.5490196347236633,
            0.8078431487083435,
            0.9882352948188782
          ],
          "alpha": 1,
          "hex": "#8CCEFC"
        },
        "$extensions": {
          "com.figma.variableId": "VariableID:4304:1171",
          "com.figma.scopes": [
            "ALL_SCOPES"
          ],
          "com.figma.aliasData": {
            "targetVariableId": "VariableID:4b91cd2065d56aabf62d534b6814e7f61470b404/-1:-1",
            "targetVariableName": "azure/80",
            "targetVariableSetId": "VariableCollectionId:83ba552c2f0e2d8b20b04cfcef7f4a43c3163632/-1:-1",
            "targetVariableSetName": "& color hero"
          }
        }
      },
      "azureLight": {
        "$type": "color",
        "$value": {
          "colorSpace": "srgb",
          "components": [
            0.5490196347236633,
            0.8078431487083435,
            0.9882352948188782
          ],
          "alpha": 0.18000000715255737,
          "hex": "#8CCEFC"
        },
        "$extensions": {
          "com.figma.variableId": "VariableID:4306:1378",
          "com.figma.scopes": [
            "ALL_SCOPES"
          ],
          "com.figma.aliasData": {
            "targetVariableId": "VariableID:22f8b3a164e1b9e7796a1bce834b61bd5bbc51c4/-1:-1",
            "targetVariableName": "azure/alphaLighter",
            "targetVariableSetId": "VariableCollectionId:83ba552c2f0e2d8b20b04cfcef7f4a43c3163632/-1:-1",
            "targetVariableSetName": "& color hero"
          }
        }
      },
      "text + icon onAzureLight": {
        "$type": "color",
        "$value": {
          "colorSpace": "srgb",
          "components": [
            0.7882353067398071,
            0.9019607901573181,
            0.9921568632125854
          ],
          "alpha": 1,
          "hex": "#C9E6FD"
        },
        "$extensions": {
          "com.figma.variableId": "VariableID:4306:1379",
          "com.figma.scopes": [
            "ALL_SCOPES"
          ],
          "com.figma.aliasData": {
            "targetVariableId": "VariableID:86970f2a549053ec4a8c49bb994673fede333277/-1:-1",
            "targetVariableName": "azure/90",
            "targetVariableSetId": "VariableCollectionId:83ba552c2f0e2d8b20b04cfcef7f4a43c3163632/-1:-1",
            "targetVariableSetName": "& color hero"
          }
        }
      },
      "blue": {
        "$type": "color",
        "$value": {
          "colorSpace": "srgb",
          "components": [
            0.6549019813537598,
            0.7843137383460999,
            0.9960784316062927
          ],
          "alpha": 1,
          "hex": "#A7C8FE"
        },
        "$extensions": {
          "com.figma.variableId": "VariableID:4304:1172",
          "com.figma.scopes": [
            "ALL_SCOPES"
          ],
          "com.figma.aliasData": {
            "targetVariableId": "VariableID:7aaf746cadc503736aac87b0dc8189d6409976c0/-1:-1",
            "targetVariableName": "blue/80",
            "targetVariableSetId": "VariableCollectionId:83ba552c2f0e2d8b20b04cfcef7f4a43c3163632/-1:-1",
            "targetVariableSetName": "& color hero"
          }
        }
      },
      "blueLight": {
        "$type": "color",
        "$value": {
          "colorSpace": "srgb",
          "components": [
            0.23137255012989044,
            0.572549045085907,
            0.9764705896377563
          ],
          "alpha": 0.18000000715255737,
          "hex": "#3B92F9"
        },
        "$extensions": {
          "com.figma.variableId": "VariableID:4306:1380",
          "com.figma.scopes": [
            "ALL_SCOPES"
          ],
          "com.figma.aliasData": {
            "targetVariableId": "VariableID:003760f77e7f7fe8481ee431b6637d9c7212359e/-1:-1",
            "targetVariableName": "blue/alphaLighter",
            "targetVariableSetId": "VariableCollectionId:83ba552c2f0e2d8b20b04cfcef7f4a43c3163632/-1:-1",
            "targetVariableSetName": "& color hero"
          }
        }
      },
      "text + icon onBlueLight": {
        "$type": "color",
        "$value": {
          "colorSpace": "srgb",
          "components": [
            0.8352941274642944,
            0.8901960849761963,
            0.9960784316062927
          ],
          "alpha": 1,
          "hex": "#D5E3FE"
        },
        "$extensions": {
          "com.figma.variableId": "VariableID:4306:1381",
          "com.figma.scopes": [
            "ALL_SCOPES"
          ],
          "com.figma.aliasData": {
            "targetVariableId": "VariableID:dd933a7dd4b38a0654237e88881bc8c515a3918c/-1:-1",
            "targetVariableName": "blue/90",
            "targetVariableSetId": "VariableCollectionId:83ba552c2f0e2d8b20b04cfcef7f4a43c3163632/-1:-1",
            "targetVariableSetName": "& color hero"
          }
        }
      },
      "indigo": {
        "$type": "color",
        "$value": {
          "colorSpace": "srgb",
          "components": [
            0.7372549176216125,
            0.7647058963775635,
            1
          ],
          "alpha": 1,
          "hex": "#BCC3FF"
        },
        "$extensions": {
          "com.figma.variableId": "VariableID:4304:1173",
          "com.figma.scopes": [
            "ALL_SCOPES"
          ],
          "com.figma.aliasData": {
            "targetVariableId": "VariableID:9399883f6c365659987d6621e53f67929dcfa6ad/-1:-1",
            "targetVariableName": "indigo/80",
            "targetVariableSetId": "VariableCollectionId:83ba552c2f0e2d8b20b04cfcef7f4a43c3163632/-1:-1",
            "targetVariableSetName": "& color hero"
          }
        }
      },
      "indigoLight": {
        "$type": "color",
        "$value": {
          "colorSpace": "srgb",
          "components": [
            0.3137255012989044,
            0.4000000059604645,
            1
          ],
          "alpha": 0.3799999952316284,
          "hex": "#5066FF"
        },
        "$extensions": {
          "com.figma.variableId": "VariableID:4306:1382",
          "com.figma.scopes": [
            "ALL_SCOPES"
          ],
          "com.figma.aliasData": {
            "targetVariableId": "VariableID:37f791e39ad16a0f052f7418398eebc428fb0ff8/-1:-1",
            "targetVariableName": "indigo/alphaLightest",
            "targetVariableSetId": "VariableCollectionId:83ba552c2f0e2d8b20b04cfcef7f4a43c3163632/-1:-1",
            "targetVariableSetName": "& color hero"
          }
        }
      },
      "text + icon onIndigoLight": {
        "$type": "color",
        "$value": {
          "colorSpace": "srgb",
          "components": [
            0.8705882430076599,
            0.8784313797950745,
            1
          ],
          "alpha": 1,
          "hex": "#DEE0FF"
        },
        "$extensions": {
          "com.figma.variableId": "VariableID:4306:1383",
          "com.figma.scopes": [
            "ALL_SCOPES"
          ],
          "com.figma.aliasData": {
            "targetVariableId": "VariableID:2de74d9c663d70e1a4fd12f96f7626116274507f/-1:-1",
            "targetVariableName": "indigo/90",
            "targetVariableSetId": "VariableCollectionId:83ba552c2f0e2d8b20b04cfcef7f4a43c3163632/-1:-1",
            "targetVariableSetName": "& color hero"
          }
        }
      },
      "violet": {
        "$type": "color",
        "$value": {
          "colorSpace": "srgb",
          "components": [
            0.8156862854957581,
            0.7372549176216125,
            1
          ],
          "alpha": 1,
          "hex": "#D0BCFF"
        },
        "$extensions": {
          "com.figma.variableId": "VariableID:4304:1174",
          "com.figma.scopes": [
            "ALL_SCOPES"
          ],
          "com.figma.aliasData": {
            "targetVariableId": "VariableID:e69f09c6112f70fc7e546a3d39a6b346a7055e31/-1:-1",
            "targetVariableName": "violet/80",
            "targetVariableSetId": "VariableCollectionId:83ba552c2f0e2d8b20b04cfcef7f4a43c3163632/-1:-1",
            "targetVariableSetName": "& color hero"
          }
        }
      },
      "violetLight": {
        "$type": "color",
        "$value": {
          "colorSpace": "srgb",
          "components": [
            0.8156862854957581,
            0.7372549176216125,
            1
          ],
          "alpha": 0.18000000715255737,
          "hex": "#D0BCFF"
        },
        "$extensions": {
          "com.figma.variableId": "VariableID:4306:1384",
          "com.figma.scopes": [
            "ALL_SCOPES"
          ],
          "com.figma.aliasData": {
            "targetVariableId": "VariableID:6184fc85a27b0312e76154dd90391a8dd7966f46/-1:-1",
            "targetVariableName": "violet/alphaLighter",
            "targetVariableSetId": "VariableCollectionId:83ba552c2f0e2d8b20b04cfcef7f4a43c3163632/-1:-1",
            "targetVariableSetName": "& color hero"
          }
        }
      },
      "text + icon onVioletLight": {
        "$type": "color",
        "$value": {
          "colorSpace": "srgb",
          "components": [
            0.9137254953384399,
            0.8666666746139526,
            1
          ],
          "alpha": 1,
          "hex": "#E9DDFF"
        },
        "$extensions": {
          "com.figma.variableId": "VariableID:4306:1385",
          "com.figma.scopes": [
            "ALL_SCOPES"
          ],
          "com.figma.aliasData": {
            "targetVariableId": "VariableID:54a30105fc349b96bae218f63fe33b8e40b1beeb/-1:-1",
            "targetVariableName": "violet/90",
            "targetVariableSetId": "VariableCollectionId:83ba552c2f0e2d8b20b04cfcef7f4a43c3163632/-1:-1",
            "targetVariableSetName": "& color hero"
          }
        }
      },
      "purple": {
        "$type": "color",
        "$value": {
          "colorSpace": "srgb",
          "components": [
            0.9215686321258545,
            0.6980392336845398,
            1
          ],
          "alpha": 1,
          "hex": "#EBB2FF"
        },
        "$extensions": {
          "com.figma.variableId": "VariableID:4304:1175",
          "com.figma.scopes": [
            "ALL_SCOPES"
          ],
          "com.figma.aliasData": {
            "targetVariableId": "VariableID:3f7a28680ef749b8bd3b07ba3ed017833eedee34/-1:-1",
            "targetVariableName": "purple/80",
            "targetVariableSetId": "VariableCollectionId:83ba552c2f0e2d8b20b04cfcef7f4a43c3163632/-1:-1",
            "targetVariableSetName": "& color hero"
          }
        }
      },
      "purpleLight": {
        "$type": "color",
        "$value": {
          "colorSpace": "srgb",
          "components": [
            0.9215686321258545,
            0.6980392336845398,
            1
          ],
          "alpha": 0.18000000715255737,
          "hex": "#EBB2FF"
        },
        "$extensions": {
          "com.figma.variableId": "VariableID:4306:1386",
          "com.figma.scopes": [
            "ALL_SCOPES"
          ],
          "com.figma.aliasData": {
            "targetVariableId": "VariableID:eac3a6cad51ee9bf5855796190855f84cbbcb9c3/-1:-1",
            "targetVariableName": "purple/alphaLighter",
            "targetVariableSetId": "VariableCollectionId:83ba552c2f0e2d8b20b04cfcef7f4a43c3163632/-1:-1",
            "targetVariableSetName": "& color hero"
          }
        }
      },
      "text + icon onPurpleLight": {
        "$type": "color",
        "$value": {
          "colorSpace": "srgb",
          "components": [
            0.9725490212440491,
            0.8470588326454163,
            1
          ],
          "alpha": 1,
          "hex": "#F8D8FF"
        },
        "$extensions": {
          "com.figma.variableId": "VariableID:4306:1387",
          "com.figma.scopes": [
            "ALL_SCOPES"
          ],
          "com.figma.aliasData": {
            "targetVariableId": "VariableID:3e39bd8ef0b461beda3b6284d66bd251248c35af/-1:-1",
            "targetVariableName": "purple/90",
            "targetVariableSetId": "VariableCollectionId:83ba552c2f0e2d8b20b04cfcef7f4a43c3163632/-1:-1",
            "targetVariableSetName": "& color hero"
          }
        }
      },
      "magenta": {
        "$type": "color",
        "$value": {
          "colorSpace": "srgb",
          "components": [
            0.9607843160629272,
            0.5098039507865906,
            0.8549019694328308
          ],
          "alpha": 1,
          "hex": "#F582DA"
        },
        "$extensions": {
          "com.figma.variableId": "VariableID:4304:1176",
          "com.figma.scopes": [
            "ALL_SCOPES"
          ],
          "com.figma.aliasData": {
            "targetVariableId": "VariableID:707601978bb03a3d42108f724676c75d32e1c489/-1:-1",
            "targetVariableName": "magenta/70",
            "targetVariableSetId": "VariableCollectionId:83ba552c2f0e2d8b20b04cfcef7f4a43c3163632/-1:-1",
            "targetVariableSetName": "& color hero"
          }
        }
      },
      "magentaLight": {
        "$type": "color",
        "$value": {
          "colorSpace": "srgb",
          "components": [
            0.9843137264251709,
            0.686274528503418,
            0.8980392217636108
          ],
          "alpha": 0.18000000715255737,
          "hex": "#FBAFE5"
        },
        "$extensions": {
          "com.figma.variableId": "VariableID:4306:1388",
          "com.figma.scopes": [
            "ALL_SCOPES"
          ],
          "com.figma.aliasData": {
            "targetVariableId": "VariableID:7cab2e5fa8c345046ecb09c3c8545f21b63aea11/-1:-1",
            "targetVariableName": "magenta/alphaLighter",
            "targetVariableSetId": "VariableCollectionId:83ba552c2f0e2d8b20b04cfcef7f4a43c3163632/-1:-1",
            "targetVariableSetName": "& color hero"
          }
        }
      },
      "text + icon onMagentaLight": {
        "$type": "color",
        "$value": {
          "colorSpace": "srgb",
          "components": [
            0.9921568632125854,
            0.8470588326454163,
            0.9372549057006836
          ],
          "alpha": 1,
          "hex": "#FDD8EF"
        },
        "$extensions": {
          "com.figma.variableId": "VariableID:4306:1389",
          "com.figma.scopes": [
            "ALL_SCOPES"
          ],
          "com.figma.aliasData": {
            "targetVariableId": "VariableID:eb0f8081aaf36dba02d7eb60ec084e9a2409e818/-1:-1",
            "targetVariableName": "magenta/90",
            "targetVariableSetId": "VariableCollectionId:83ba552c2f0e2d8b20b04cfcef7f4a43c3163632/-1:-1",
            "targetVariableSetName": "& color hero"
          }
        }
      },
      "pink": {
        "$type": "color",
        "$value": {
          "colorSpace": "srgb",
          "components": [
            0.9882352948188782,
            0.5215686559677124,
            0.6823529601097107
          ],
          "alpha": 1,
          "hex": "#FC85AE"
        },
        "$extensions": {
          "com.figma.variableId": "VariableID:4304:1177",
          "com.figma.scopes": [
            "ALL_SCOPES"
          ],
          "com.figma.aliasData": {
            "targetVariableId": "VariableID:5739a05ea45b59e4b7235a6542c530617f610987/-1:-1",
            "targetVariableName": "pink/70",
            "targetVariableSetId": "VariableCollectionId:83ba552c2f0e2d8b20b04cfcef7f4a43c3163632/-1:-1",
            "targetVariableSetName": "& color hero"
          }
        }
      },
      "pinkLight": {
        "$type": "color",
        "$value": {
          "colorSpace": "srgb",
          "components": [
            0.9921568632125854,
            0.6941176652908325,
            0.7843137383460999
          ],
          "alpha": 0.18000000715255737,
          "hex": "#FDB1C8"
        },
        "$extensions": {
          "com.figma.variableId": "VariableID:4306:1390",
          "com.figma.scopes": [
            "ALL_SCOPES"
          ],
          "com.figma.aliasData": {
            "targetVariableId": "VariableID:c323f66efb87e7bad84dac6fe50fce90112404b9/-1:-1",
            "targetVariableName": "pink/alphaLighter",
            "targetVariableSetId": "VariableCollectionId:83ba552c2f0e2d8b20b04cfcef7f4a43c3163632/-1:-1",
            "targetVariableSetName": "& color hero"
          }
        }
      },
      "text + icon onPinkLight": {
        "$type": "color",
        "$value": {
          "colorSpace": "srgb",
          "components": [
            1,
            0.8509804010391235,
            0.886274516582489
          ],
          "alpha": 1,
          "hex": "#FFD9E2"
        },
        "$extensions": {
          "com.figma.variableId": "VariableID:4306:1391",
          "com.figma.scopes": [
            "ALL_SCOPES"
          ],
          "com.figma.aliasData": {
            "targetVariableId": "VariableID:ac31744e8a1023a1187fbfd413828dd6e3872462/-1:-1",
            "targetVariableName": "pink/90",
            "targetVariableSetId": "VariableCollectionId:83ba552c2f0e2d8b20b04cfcef7f4a43c3163632/-1:-1",
            "targetVariableSetName": "& color hero"
          }
        }
      }
    }
  },
  "$extensions": {
    "com.figma.modeName": "Dark.a"
  }
}